sdat2img_brotli/__init__.py
sdat2img_brotli/main.py
sdat2img_brotli-1.0.3.dist-info/LICENSE.txt
sdat2img_brotli-1.0.3.dist-info/METADATA
sdat2img_brotli-1.0.3.dist-info/WHEEL
sdat2img_brotli-1.0.3.dist-info/entry_points.txt
sdat2img_brotli-1.0.3.dist-info/top_level.txt
sdat2img_brotli-1.0.3.dist-info/RECORD
