Metadata-Version: 2.1
Name: sdat2img-brotli
Version: 1.0.3
Summary: A Python tool to decompress .dat.br files and convert Android .dat/.transfer.list into .img disk images.
Home-page: https://github.com/tntapple219/sdat2img_brotli_forPyPI
Author: TNTAPPLE
Author-email: tntapple219@gmail.com
Classifier: Programming Language :: Python :: 3
Classifier: Programming Language :: Python :: 3.6
Classifier: Programming Language :: Python :: 3.7
Classifier: Programming Language :: Python :: 3.8
Classifier: Programming Language :: Python :: 3.9
Classifier: Programming Language :: Python :: 3.10
Classifier: Programming Language :: Python :: 3.11
Classifier: Programming Language :: Python :: 3.12
Classifier: License :: OSI Approved :: MIT License
Classifier: Operating System :: OS Independent
Classifier: Topic :: System :: Archiving
Classifier: Topic :: Utilities
Requires-Python: >=3.6
License-File: LICENSE.txt
Requires-Dist: brotli
